Products.MIMETools-4.0-py3.11-nspkg.pth
Products/MIMETools/MIMETag.py
Products/MIMETools/__init__.py
Products/MIMETools/tests.py
Products.MIMETools-4.0.dist-info/LICENSE.txt
Products.MIMETools-4.0.dist-info/METADATA
Products.MIMETools-4.0.dist-info/WHEEL
Products.MIMETools-4.0.dist-info/namespace_packages.txt
Products.MIMETools-4.0.dist-info/top_level.txt
Products.MIMETools-4.0.dist-info/RECORD
