Metadata-Version: 2.1
Name: Products.MIMETools
Version: 4.0
Summary: MIMETools provides the ``dtml-mime`` tag for DocumentTemplate.
Home-page: https://github.com/zopefoundation/Products.MIMETools
Author: Zope Foundation and Contributors
Author-email: zope-dev@zope.dev
License: ZPL 2.1
Project-URL: Issue Tracker, https://github.com/zopefoundation/Products.MIMETools/issues
Project-URL: Sources, https://github.com/zopefoundation/Products.MIMETools
Classifier: Development Status :: 6 - Mature
Classifier: Environment :: Web Environment
Classifier: Framework :: Zope
Classifier: Framework :: Zope :: 5
Classifier: License :: OSI Approved :: Zope Public License
Classifier: Operating System :: OS Independent
Classifier: Programming Language :: Python :: 3
Classifier: Programming Language :: Python :: 3.7
Classifier: Programming Language :: Python :: 3.8
Classifier: Programming Language :: Python :: 3.9
Classifier: Programming Language :: Python :: 3.10
Classifier: Programming Language :: Python :: 3.11
Classifier: Programming Language :: Python :: Implementation :: CPython
Classifier: Topic :: Communications :: Email
Requires-Python: >=3.7
License-File: LICENSE.txt
Requires-Dist: setuptools
Requires-Dist: ExtensionClass (>=4.1a1)
Requires-Dist: DocumentTemplate (>=3)
